setup.py
MyPagePlugin/MyPagePlugin.py
TracMyPagePlugin.egg-info/PKG-INFO
TracMyPagePlugin.egg-info/SOURCES.txt
TracMyPagePlugin.egg-info/dependency_links.txt
TracMyPagePlugin.egg-info/entry_points.txt
TracMyPagePlugin.egg-info/top_level.txt
TracMyPagePlugin.egg-info/zip-safe