Metadata-Version: 1.0
Name: TracMyPagePlugin
Version: 0.11.1.1
Summary: My Page navigation bar tab for Trac
Home-page: http://trac-hacks.org/wiki/TracMyPagePlugin
Author: David Champion
Author-email: dgc@uchicago.edu
License: 
